{
  "users": [],
  "doctor_applications": [],
  "medicines": [],
  "medicine_history": [],
  "medicine_notifications": [],
  "medicine_notification_prefs": [],
  "forum_posts": [],
  "forum_replies": [],
  "symptom_logs": [],
  "clinical_cases": [],
  "case_collections": [],
  "ai_chat_evaluations": [],
  "ai_chat_sessions": [],
  "ai_chat_histories": [],
  "doctor_reply_training_samples": [],
  "two_factor_challenges": [],
  "email_verification_challenges": [],
  "user_profiles": [],
  "bookmarks": [],
  "tutorial_status": [],
  "admin_logs": [],
  "health_articles": [],
  "health_news_events": [],
  "medical_facilities": []
}
